matrixgale/__init__.py
matrixgale/gmat.py
matrixgale-0.1.dist-info/LICENCE.txt
matrixgale-0.1.dist-info/METADATA
matrixgale-0.1.dist-info/WHEEL
matrixgale-0.1.dist-info/top_level.txt
matrixgale-0.1.dist-info/RECORD
