Metadata-Version: 2.1
Name: matrixgale
Version: 0.1
Summary: New python library for work with Matrices. New additional userfriendly features are available for Math purposes
Home-page: UNKNOWN
Author: Gallella M.M.H.H.B.
Author-email: solve.with.hb@gmail.com
License: UNKNOWN
Platform: UNKNOWN
Classifier: Programming Language :: Python :: 3
Classifier: License :: OSI Approved :: MIT License
Classifier: Operating System :: OS Independent
License-File: LICENCE.txt
